config/.env
config/__init__.py
config/database_config.json
config/dbconfig.py
config/event_store.py
connection/__init__.py
connection/connection_pool.py
connection/pool_creator.py
connection/pool_manager.py
core/__init__.py
core/exceptions.py
core/server.py
databases/__init__.py
databases/database_factory.py
databases/base/__init__.py
databases/base/base.py
databases/mssqlserver/__init__.py
databases/mssqlserver/mssqlserver_db_version.py
databases/mssqlserver/mssqlserver_health.py
databases/mssqlserver/mssqlserver_optimize.py
databases/mssqlserver/mssqlserver_queries.py
databases/mssqlserver/mssqlserver_table_description.py
databases/mssqlserver/mssqlserver_table_index.py
databases/mssqlserver/mssqlserver_table_name.py
databases/mssqlserver/sqlserver_factory.py
databases/mysql/__init__.py
databases/mysql/mysql_db_version.py
databases/mysql/mysql_factory.py
databases/mysql/mysql_health.py
databases/mysql/mysql_optimize.py
databases/mysql/mysql_queries.py
databases/mysql/mysql_table_description.py
databases/mysql/mysql_table_index.py
databases/mysql/mysql_table_name.py
databases/oracle/__init__.py
databases/oracle/oracle_db_version.py
databases/oracle/oracle_factory.py
databases/oracle/oracle_health.py
databases/oracle/oracle_optimize.py
databases/oracle/oracle_queries.py
databases/oracle/oracle_table_description.py
databases/oracle/oracle_table_index.py
databases/oracle/oracle_table_name.py
databases/postgresql/__init__.py
databases/postgresql/postgresql_db_version.py
databases/postgresql/postgresql_factory.py
databases/postgresql/postgresql_health.py
databases/postgresql/postgresql_optimize.py
databases/postgresql/postgresql_queries.py
databases/postgresql/postgresql_table_description.py
databases/postgresql/postgresql_table_index.py
databases/postgresql/postgresql_table_name.py
oauth/__init__.py
oauth/middleware.py
oauth/oauth_config.py
oauth/routes.py
oauth/token_handler.py
static/login/config.js
static/login/index.html
smartdb_mcp-1.0.0.dist-info/METADATA
smartdb_mcp-1.0.0.dist-info/WHEEL
smartdb_mcp-1.0.0.dist-info/entry_points.txt
smartdb_mcp-1.0.0.dist-info/RECORD
